arenadata_pylint_plugin/__init__.py
arenadata_pylint_plugin/assertion_message.py
arenadata_pylint_plugin-0.1.0.dist-info/LICENSE
arenadata_pylint_plugin-0.1.0.dist-info/METADATA
arenadata_pylint_plugin-0.1.0.dist-info/WHEEL
arenadata_pylint_plugin-0.1.0.dist-info/top_level.txt
arenadata_pylint_plugin-0.1.0.dist-info/RECORD
